[
  {
    "id": 1,
    "vehicle_type": "bus",
    "brand": "Pixoboo",
    "number_of_seats": 23,
    "photo_url": "http://addthis.com/morbi/sem/mauris/laoreet/ut/rhoncus.xml"
  },
  {
    "id": 2,
    "vehicle_type": "personal_car",
    "brand": "Gigaclub",
    "number_of_seats": 18,
    "photo_url": "https://patch.com/sit.jsp"
  },
  {
    "id": 3,
    "vehicle_type": "bus",
    "brand": "Youopia",
    "number_of_seats": 2,
    "photo_url": "http://sina.com.cn/vestibulum/sed/magna.jsp"
  },
  {
    "id": 4,
    "vehicle_type": "bus",
    "brand": "Omba",
    "number_of_seats": 6,
    "photo_url": "https://sitemeter.com/turpis/integer/aliquet/massa/id/lobortis/convallis.html"
  },
  {
    "id": 5,
    "vehicle_type": "taxi",
    "brand": "Twimm",
    "number_of_seats": 21,
    "photo_url": "https://webnode.com/in.png"
  },
  {
    "id": 6,
    "vehicle_type": "bike",
    "brand": "Reallinks",
    "number_of_seats": 9,
    "photo_url": "http://usgs.gov/aliquet/massa/id/lobortis/convallis.js"
  },
  {
    "id": 7,
    "vehicle_type": "taxi",
    "brand": "Linkbridge",
    "number_of_seats": 9,
    "photo_url": "http://lulu.com/eu/nibh/quisque/id/justo/sit.json"
  },
  {
    "id": 8,
    "vehicle_type": "bike",
    "brand": "Oyope",
    "number_of_seats": 2,
    "photo_url": "http://bbc.co.uk/volutpat/eleifend.xml"
  },
  {
    "id": 9,
    "vehicle_type": "personal_car",
    "brand": "Twimm",
    "number_of_seats": 11,
    "photo_url": "https://moonfruit.com/molestie/sed/justo/pellentesque/viverra.xml"
  },
  {
    "id": 10,
    "vehicle_type": "personal_car",
    "brand": "Gigashots",
    "number_of_seats": 6,
    "photo_url": "https://reverbnation.com/nascetur/ridiculus/mus.js"
  },
  {
    "id": 11,
    "vehicle_type": "personal_car",
    "brand": "Photojam",
    "number_of_seats": 16,
    "photo_url": "http://cbc.ca/lacus/morbi/quis/tortor/id/nulla.aspx"
  },
  {
    "id": 12,
    "vehicle_type": "bike",
    "brand": "Kimia",
    "number_of_seats": 7,
    "photo_url": "https://flavors.me/aliquam/quis/turpis/eget/elit.jpg"
  },
  {
    "id": 13,
    "vehicle_type": "bus",
    "brand": "Skyba",
    "number_of_seats": 5,
    "photo_url": "http://ezinearticles.com/vestibulum/proin/eu/mi.png"
  },
  {
    "id": 14,
    "vehicle_type": "bike",
    "brand": "Brainsphere",
    "number_of_seats": 11,
    "photo_url": "http://earthlink.net/lectus/suspendisse/potenti/in/eleifend/quam.html"
  },
  {
    "id": 15,
    "vehicle_type": "taxi",
    "brand": "Quatz",
    "number_of_seats": 6,
    "photo_url": "http://prlog.org/justo/lacinia/eget/tincidunt.js"
  },
  {
    "id": 16,
    "vehicle_type": "personal_car",
    "brand": "Realcube",
    "number_of_seats": 15,
    "photo_url": "http://uol.com.br/sapien/ut.html"
  },
  {
    "id": 17,
    "vehicle_type": "bus",
    "brand": "Dabjam",
    "number_of_seats": 26,
    "photo_url": "http://telegraph.co.uk/turpis/adipiscing/lorem.jpg"
  },
  {
    "id": 18,
    "vehicle_type": "bus",
    "brand": "Thoughtblab",
    "number_of_seats": 24,
    "photo_url": "http://japanpost.jp/orci/eget/orci/vehicula.xml"
  },
  {
    "id": 19,
    "vehicle_type": "taxi",
    "brand": "Voonder",
    "number_of_seats": 21,
    "photo_url": "http://virginia.edu/eros/elementum/pellentesque/quisque/porta/volutpat/erat.jsp"
  },
  {
    "id": 20,
    "vehicle_type": "bus",
    "brand": "Aimbo",
    "number_of_seats": 6,
    "photo_url": "http://wikipedia.org/ultrices/phasellus/id/sapien.json"
  },
  {
    "id": 21,
    "vehicle_type": "taxi",
    "brand": "Photolist",
    "number_of_seats": 22,
    "photo_url": "http://columbia.edu/in/faucibus/orci/luctus/et/ultrices/posuere.aspx"
  },
  {
    "id": 22,
    "vehicle_type": "taxi",
    "brand": "Eamia",
    "number_of_seats": 15,
    "photo_url": "http://whitehouse.gov/sed/interdum/venenatis/turpis/enim/blandit.json"
  },
  {
    "id": 23,
    "vehicle_type": "bike",
    "brand": "Yacero",
    "number_of_seats": 28,
    "photo_url": "https://sakura.ne.jp/habitasse.html"
  },
  {
    "id": 24,
    "vehicle_type": "personal_car",
    "brand": "Photobug",
    "number_of_seats": 12,
    "photo_url": "https://paypal.com/a/nibh.aspx"
  },
  {
    "id": 25,
    "vehicle_type": "bus",
    "brand": "Feedbug",
    "number_of_seats": 12,
    "photo_url": "https://free.fr/nulla/mollis/molestie.html"
  },
  {
    "id": 26,
    "vehicle_type": "personal_car",
    "brand": "Thoughtbridge",
    "number_of_seats": 24,
    "photo_url": "http://mozilla.com/in/magna/bibendum/imperdiet/nullam.json"
  },
  {
    "id": 27,
    "vehicle_type": "bus",
    "brand": "Zazio",
    "number_of_seats": 25,
    "photo_url": "https://biglobe.ne.jp/urna/pretium/nisl/ut/volutpat/sapien/arcu.html"
  },
  {
    "id": 28,
    "vehicle_type": "bike",
    "brand": "Yoveo",
    "number_of_seats": 12,
    "photo_url": "https://quantcast.com/sapien/cum.jsp"
  },
  {
    "id": 29,
    "vehicle_type": "bike",
    "brand": "Ooba",
    "number_of_seats": 27,
    "photo_url": "http://biblegateway.com/convallis/nulla.jsp"
  },
  {
    "id": 30,
    "vehicle_type": "personal_car",
    "brand": "Eamia",
    "number_of_seats": 26,
    "photo_url": "http://de.vu/in/tempor/turpis.json"
  },
  {
    "id": 31,
    "vehicle_type": "personal_car",
    "brand": "Photobug",
    "number_of_seats": 30,
    "photo_url": "https://sourceforge.net/nonummy/integer/non/velit/donec/diam/neque.jsp"
  },
  {
    "id": 32,
    "vehicle_type": "taxi",
    "brand": "Zoonder",
    "number_of_seats": 9,
    "photo_url": "https://weebly.com/amet/lobortis/sapien/sapien/non/mi.jpg"
  },
  {
    "id": 33,
    "vehicle_type": "bike",
    "brand": "Babbleblab",
    "number_of_seats": 2,
    "photo_url": "https://tumblr.com/proin/eu/mi/nulla.png"
  },
  {
    "id": 34,
    "vehicle_type": "personal_car",
    "brand": "Realpoint",
    "number_of_seats": 25,
    "photo_url": "https://cocolog-nifty.com/morbi/vestibulum/velit/id/pretium/iaculis.aspx"
  },
  {
    "id": 35,
    "vehicle_type": "personal_car",
    "brand": "Skimia",
    "number_of_seats": 6,
    "photo_url": "http://stumbleupon.com/varius/nulla/facilisi.js"
  },
  {
    "id": 36,
    "vehicle_type": "personal_car",
    "brand": "Skyble",
    "number_of_seats": 27,
    "photo_url": "https://slideshare.net/sit/amet/justo/morbi/ut.json"
  },
  {
    "id": 37,
    "vehicle_type": "bike",
    "brand": "Kayveo",
    "number_of_seats": 4,
    "photo_url": "https://google.pl/vestibulum/sed/magna/at/nunc.aspx"
  },
  {
    "id": 38,
    "vehicle_type": "taxi",
    "brand": "Flipopia",
    "number_of_seats": 23,
    "photo_url": "http://instagram.com/congue/eget/semper/rutrum.jpg"
  },
  {
    "id": 39,
    "vehicle_type": "personal_car",
    "brand": "Rhynoodle",
    "number_of_seats": 21,
    "photo_url": "https://wp.com/est/quam/pharetra/magna.png"
  },
  {
    "id": 40,
    "vehicle_type": "bus",
    "brand": "Tagfeed",
    "number_of_seats": 20,
    "photo_url": "http://a8.net/diam/erat/fermentum/justo/nec.jpg"
  },
  {
    "id": 41,
    "vehicle_type": "bus",
    "brand": "Meevee",
    "number_of_seats": 21,
    "photo_url": "https://statcounter.com/mattis/pulvinar/nulla/pede.json"
  },
  {
    "id": 42,
    "vehicle_type": "bike",
    "brand": "Jayo",
    "number_of_seats": 10,
    "photo_url": "https://furl.net/vulputate/nonummy/maecenas.js"
  },
  {
    "id": 43,
    "vehicle_type": "bike",
    "brand": "Trudoo",
    "number_of_seats": 21,
    "photo_url": "http://youtu.be/molestie/sed/justo/pellentesque/viverra/pede.html"
  },
  {
    "id": 44,
    "vehicle_type": "personal_car",
    "brand": "Kare",
    "number_of_seats": 4,
    "photo_url": "http://yahoo.com/eu/tincidunt/in/leo/maecenas/pulvinar.png"
  },
  {
    "id": 45,
    "vehicle_type": "personal_car",
    "brand": "Yoveo",
    "number_of_seats": 20,
    "photo_url": "https://flavors.me/luctus/nec.jsp"
  },
  {
    "id": 46,
    "vehicle_type": "taxi",
    "brand": "Buzzdog",
    "number_of_seats": 7,
    "photo_url": "http://shareasale.com/platea/dictumst/morbi/vestibulum/velit/id/pretium.png"
  },
  {
    "id": 47,
    "vehicle_type": "taxi",
    "brand": "Skidoo",
    "number_of_seats": 26,
    "photo_url": "http://paypal.com/ut/ultrices/vel/augue.jpg"
  },
  {
    "id": 48,
    "vehicle_type": "taxi",
    "brand": "Jabbersphere",
    "number_of_seats": 15,
    "photo_url": "http://columbia.edu/velit/nec/nisi/vulputate.jpg"
  },
  {
    "id": 49,
    "vehicle_type": "bus",
    "brand": "Voolith",
    "number_of_seats": 9,
    "photo_url": "http://nymag.com/id/justo/sit/amet.json"
  },
  {
    "id": 50,
    "vehicle_type": "bus",
    "brand": "Vitz",
    "number_of_seats": 5,
    "photo_url": "https://bandcamp.com/porttitor.html"
  },
  {
    "id": 51,
    "vehicle_type": "personal_car",
    "brand": "Voonte",
    "number_of_seats": 23,
    "photo_url": "https://webeden.co.uk/lorem/ipsum/dolor/sit.aspx"
  },
  {
    "id": 52,
    "vehicle_type": "taxi",
    "brand": "Demizz",
    "number_of_seats": 26,
    "photo_url": "https://over-blog.com/donec/odio/justo/sollicitudin.png"
  },
  {
    "id": 53,
    "vehicle_type": "personal_car",
    "brand": "Ozu",
    "number_of_seats": 14,
    "photo_url": "https://hc360.com/morbi/quis/tortor.xml"
  },
  {
    "id": 54,
    "vehicle_type": "bike",
    "brand": "Twitterbeat",
    "number_of_seats": 19,
    "photo_url": "http://vimeo.com/congue/risus/semper.png"
  },
  {
    "id": 55,
    "vehicle_type": "personal_car",
    "brand": "Voolia",
    "number_of_seats": 21,
    "photo_url": "http://whitehouse.gov/quam/sollicitudin/vitae/consectetuer/eget/rutrum/at.jpg"
  },
  {
    "id": 56,
    "vehicle_type": "bike",
    "brand": "Jabberstorm",
    "number_of_seats": 4,
    "photo_url": "https://woothemes.com/rhoncus/dui/vel/sem/sed/sagittis/nam.html"
  },
  {
    "id": 57,
    "vehicle_type": "taxi",
    "brand": "Wordify",
    "number_of_seats": 8,
    "photo_url": "https://squarespace.com/primis/in/faucibus/orci.json"
  },
  {
    "id": 58,
    "vehicle_type": "taxi",
    "brand": "Topicshots",
    "number_of_seats": 27,
    "photo_url": "http://columbia.edu/dolor/morbi/vel/lectus.png"
  },
  {
    "id": 59,
    "vehicle_type": "taxi",
    "brand": "Browsezoom",
    "number_of_seats": 13,
    "photo_url": "http://mashable.com/cum/sociis/natoque/penatibus/et/magnis.aspx"
  },
  {
    "id": 60,
    "vehicle_type": "personal_car",
    "brand": "Skynoodle",
    "number_of_seats": 5,
    "photo_url": "http://rambler.ru/curabitur/gravida/nisi/at/nibh/in/hac.jpg"
  },
  {
    "id": 61,
    "vehicle_type": "bike",
    "brand": "Bluejam",
    "number_of_seats": 18,
    "photo_url": "http://cpanel.net/proin/interdum/mauris.json"
  },
  {
    "id": 62,
    "vehicle_type": "taxi",
    "brand": "Divanoodle",
    "number_of_seats": 4,
    "photo_url": "http://shop-pro.jp/blandit/mi/in.xml"
  },
  {
    "id": 63,
    "vehicle_type": "bus",
    "brand": "Topdrive",
    "number_of_seats": 2,
    "photo_url": "https://google.de/congue.html"
  },
  {
    "id": 64,
    "vehicle_type": "taxi",
    "brand": "Digitube",
    "number_of_seats": 3,
    "photo_url": "http://omniture.com/et/commodo/vulputate.html"
  },
  {
    "id": 65,
    "vehicle_type": "bike",
    "brand": "Cogibox",
    "number_of_seats": 4,
    "photo_url": "https://princeton.edu/tristique/in/tempus.aspx"
  },
  {
    "id": 66,
    "vehicle_type": "bus",
    "brand": "Vipe",
    "number_of_seats": 19,
    "photo_url": "https://goo.ne.jp/felis/eu.json"
  },
  {
    "id": 67,
    "vehicle_type": "personal_car",
    "brand": "Quamba",
    "number_of_seats": 5,
    "photo_url": "https://reuters.com/odio/cras/mi/pede/malesuada/in/imperdiet.jsp"
  },
  {
    "id": 68,
    "vehicle_type": "personal_car",
    "brand": "Kwideo",
    "number_of_seats": 2,
    "photo_url": "https://networksolutions.com/lobortis.json"
  },
  {
    "id": 69,
    "vehicle_type": "bus",
    "brand": "Gabtype",
    "number_of_seats": 6,
    "photo_url": "http://wix.com/nonummy/maecenas/tincidunt/lacus.aspx"
  },
  {
    "id": 70,
    "vehicle_type": "bus",
    "brand": "Wikido",
    "number_of_seats": 6,
    "photo_url": "https://netscape.com/pede/justo/lacinia/eget/tincidunt/eget/tempus.aspx"
  },
  {
    "id": 71,
    "vehicle_type": "bike",
    "brand": "Photojam",
    "number_of_seats": 30,
    "photo_url": "https://list-manage.com/semper/interdum/mauris.xml"
  },
  {
    "id": 72,
    "vehicle_type": "taxi",
    "brand": "Feedfish",
    "number_of_seats": 18,
    "photo_url": "https://networksolutions.com/mauris/eget/massa/tempor/convallis/nulla.aspx"
  },
  {
    "id": 73,
    "vehicle_type": "personal_car",
    "brand": "Oodoo",
    "number_of_seats": 26,
    "photo_url": "http://jalbum.net/ac/nibh.js"
  },
  {
    "id": 74,
    "vehicle_type": "bus",
    "brand": "Plajo",
    "number_of_seats": 5,
    "photo_url": "https://sphinn.com/in/imperdiet/et/commodo/vulputate.png"
  },
  {
    "id": 75,
    "vehicle_type": "bike",
    "brand": "Meevee",
    "number_of_seats": 21,
    "photo_url": "https://umn.edu/hac/habitasse/platea/dictumst/maecenas/ut.png"
  },
  {
    "id": 76,
    "vehicle_type": "personal_car",
    "brand": "Realbridge",
    "number_of_seats": 18,
    "photo_url": "https://slideshare.net/vel/augue/vestibulum/rutrum/rutrum.jsp"
  },
  {
    "id": 77,
    "vehicle_type": "taxi",
    "brand": "Ozu",
    "number_of_seats": 19,
    "photo_url": "https://phoca.cz/fusce/consequat/nulla/nisl.png"
  },
  {
    "id": 78,
    "vehicle_type": "personal_car",
    "brand": "Oba",
    "number_of_seats": 12,
    "photo_url": "https://shutterfly.com/vestibulum/ac.xml"
  },
  {
    "id": 79,
    "vehicle_type": "personal_car",
    "brand": "Brainlounge",
    "number_of_seats": 20,
    "photo_url": "http://ox.ac.uk/montes/nascetur/ridiculus/mus.js"
  },
  {
    "id": 80,
    "vehicle_type": "taxi",
    "brand": "Ooba",
    "number_of_seats": 26,
    "photo_url": "https://biglobe.ne.jp/tincidunt/nulla/mollis/molestie.jpg"
  },
  {
    "id": 81,
    "vehicle_type": "personal_car",
    "brand": "Roombo",
    "number_of_seats": 30,
    "photo_url": "http://freewebs.com/vitae/nisl/aenean/lectus/pellentesque.jsp"
  },
  {
    "id": 82,
    "vehicle_type": "taxi",
    "brand": "Feedfish",
    "number_of_seats": 29,
    "photo_url": "http://blog.com/condimentum/neque/sapien.xml"
  },
  {
    "id": 83,
    "vehicle_type": "bus",
    "brand": "Tagtune",
    "number_of_seats": 17,
    "photo_url": "https://over-blog.com/a.json"
  },
  {
    "id": 84,
    "vehicle_type": "taxi",
    "brand": "Gabvine",
    "number_of_seats": 22,
    "photo_url": "http://cdbaby.com/erat/id/mauris/vulputate/elementum/nullam/varius.jpg"
  },
  {
    "id": 85,
    "vehicle_type": "bus",
    "brand": "Thoughtworks",
    "number_of_seats": 2,
    "photo_url": "http://liveinternet.ru/ullamcorper/augue/a/suscipit/nulla/elit/ac.png"
  },
  {
    "id": 86,
    "vehicle_type": "taxi",
    "brand": "Feedmix",
    "number_of_seats": 25,
    "photo_url": "https://prnewswire.com/bibendum/morbi/non/quam/nec/dui.html"
  },
  {
    "id": 87,
    "vehicle_type": "personal_car",
    "brand": "Twitternation",
    "number_of_seats": 29,
    "photo_url": "https://ed.gov/ut/volutpat/sapien/arcu/sed/augue.jpg"
  },
  {
    "id": 88,
    "vehicle_type": "bus",
    "brand": "Trupe",
    "number_of_seats": 29,
    "photo_url": "https://theguardian.com/nam/nulla/integer/pede.xml"
  },
  {
    "id": 89,
    "vehicle_type": "bike",
    "brand": "Flashdog",
    "number_of_seats": 1,
    "photo_url": "https://theglobeandmail.com/lobortis/sapien/sapien.html"
  },
  {
    "id": 90,
    "vehicle_type": "taxi",
    "brand": "Zava",
    "number_of_seats": 29,
    "photo_url": "https://51.la/et/ultrices/posuere/cubilia/curae/nulla/dapibus.png"
  },
  {
    "id": 91,
    "vehicle_type": "personal_car",
    "brand": "Fanoodle",
    "number_of_seats": 6,
    "photo_url": "https://elegantthemes.com/neque.js"
  },
  {
    "id": 92,
    "vehicle_type": "bus",
    "brand": "Trunyx",
    "number_of_seats": 27,
    "photo_url": "http://google.com.au/ligula.jsp"
  },
  {
    "id": 93,
    "vehicle_type": "taxi",
    "brand": "Lazzy",
    "number_of_seats": 3,
    "photo_url": "https://mtv.com/in/lacus/curabitur/at/ipsum.jsp"
  },
  {
    "id": 94,
    "vehicle_type": "bike",
    "brand": "Jabbersphere",
    "number_of_seats": 13,
    "photo_url": "https://amazon.de/phasellus/in/felis.html"
  },
  {
    "id": 95,
    "vehicle_type": "bus",
    "brand": "Npath",
    "number_of_seats": 20,
    "photo_url": "https://sourceforge.net/nam/congue/risus/semper/porta.json"
  },
  {
    "id": 96,
    "vehicle_type": "taxi",
    "brand": "Quinu",
    "number_of_seats": 24,
    "photo_url": "http://nyu.edu/vulputate/luctus/cum/sociis.js"
  },
  {
    "id": 97,
    "vehicle_type": "bus",
    "brand": "Wordpedia",
    "number_of_seats": 8,
    "photo_url": "https://newyorker.com/lobortis/est.jpg"
  },
  {
    "id": 98,
    "vehicle_type": "taxi",
    "brand": "Yambee",
    "number_of_seats": 19,
    "photo_url": "http://google.de/vivamus/vestibulum/sagittis/sapien/cum/sociis.html"
  },
  {
    "id": 99,
    "vehicle_type": "taxi",
    "brand": "Thoughtmix",
    "number_of_seats": 24,
    "photo_url": "https://163.com/integer/tincidunt/ante/vel.html"
  },
  {
    "id": 100,
    "vehicle_type": "taxi",
    "brand": "Katz",
    "number_of_seats": 2,
    "photo_url": "http://nifty.com/odio/condimentum/id/luctus/nec/molestie/sed.html"
  }
]